gtfstool/__init__.py
gtfstool/dtype_gtfs.json
gtfstool/schedule.py
gtfstool-0.0.1.dist-info/LICENSE
gtfstool-0.0.1.dist-info/METADATA
gtfstool-0.0.1.dist-info/WHEEL
gtfstool-0.0.1.dist-info/top_level.txt
gtfstool-0.0.1.dist-info/RECORD
