Metadata-Version: 2.1
Name: gtfstool
Version: 0.0.1
Summary: Python package to read, process and analyse GTFS Schedule and Realtime datasets
Home-page: https://github.com/teckkean/gtfstool
Author: teckkean
Author-email: Teck@OneMetis.com
Project-URL: Bug Tracker, https://github.com/teckkean/gtfstool/issues
Classifier: Programming Language :: Python :: 3
Classifier: License :: OSI Approved :: MIT License
Classifier: Operating System :: OS Independent
Requires-Python: >=3.9
License-File: LICENSE
